climperiods/__init__.py
climperiods/climperiods.py
climperiods-0.0.3.dist-info/METADATA
climperiods-0.0.3.dist-info/WHEEL
climperiods-0.0.3.dist-info/licenses/LICENSE
climperiods-0.0.3.dist-info/RECORD
