Metadata-Version: 2.3
Name: climperiods
Version: 0.0.3
Summary: Calculate NOAA climate averaging periods
Project-URL: Homepage, https://github.com/MutaharChalmers/climperiods
Author-email: Mutahar Chalmers <mutahar.chalmers@gmail.com>
License: MIT License
License-File: LICENSE
Classifier: Development Status :: 4 - Beta
Classifier: Intended Audience :: Science/Research
Classifier: License :: OSI Approved :: MIT License
Classifier: Operating System :: OS Independent
Classifier: Programming Language :: Python :: 3
Classifier: Topic :: Scientific/Engineering
Requires-Python: >=3.8
Requires-Dist: pandas>=1.0
